ndex/__init__.py
ndex/client.py
ndex/create_aspect.py
ndex/ndexGraphBuilder.py
ndex/networkn.py
ndex/beta/__init__.py
ndex/beta/layouts.py
ndex/beta/path_scoring.py
ndex/beta/toolbox.py
ndex/beta/test/__init__.py
ndex/beta/test/betascratchtests.py
ndex/test/__init__.py
ndex/test/non_unittest_testing.py
ndex/test/scratch_test_networkn.py
ndex/test/scratchtests.py
ndex/test/test_NdexClient.py
ndex/test/test_NetworkNConstructor.py
ndex/test/test_ProvenanceAndProfile.py
ndex/test/test_UpdatingNsetProperty.py
ndex/test/test_network.py
ndex/test/test_networkn.py
ndex/test/test_properties.py
ndex/test/test_query.py
ndex/test/test_set_get_sample.py
ndex/test/test_setting_visibility.py
ndex/test/test_system_properties.py
ndex/test/test_user.py
ndex_dev-3.0.11.41.dist-info/DESCRIPTION.rst
ndex_dev-3.0.11.41.dist-info/METADATA
ndex_dev-3.0.11.41.dist-info/RECORD
ndex_dev-3.0.11.41.dist-info/WHEEL
ndex_dev-3.0.11.41.dist-info/metadata.json
ndex_dev-3.0.11.41.dist-info/top_level.txt
