Metadata-Version: 2.0
Name: ndex-dev
Version: 3.0.11.41
Summary: NDEx Python includes a client and a data model.
Home-page: https://www.ndexbio.org
Author: The NDEx Project
Author-email: contact@ndexbio.org
License: BSD
Keywords: network analysis biology
Platform: UNKNOWN
Classifier: Development Status :: 4 - Beta
Classifier: Intended Audience :: Science/Research
Classifier: Topic :: Scientific/Engineering :: Information Analysis
Classifier: Topic :: Scientific/Engineering :: Bio-Informatics
Classifier: Topic :: Scientific/Engineering :: Medical Science Apps.
Classifier: License :: OSI Approved :: BSD License
Classifier: Programming Language :: Python :: 2.7
Requires-Dist: networkx (==1.11)
Requires-Dist: requests
Requires-Dist: requests-toolbelt
Requires-Dist: urllib3 (>=1.16)
